rest_bs/__init__.py
rest_bs/rest.py
websocket_bs/__init__.py
websocket_bs/client.py
binanceus_python-0.1.0.dist-info/LICENSE
binanceus_python-0.1.0.dist-info/WHEEL
binanceus_python-0.1.0.dist-info/METADATA
binanceus_python-0.1.0.dist-info/RECORD
