Metadata-Version: 2.1
Name: binanceus-python
Version: 0.1.0
Summary: A lightweight Python wrapper for the binance.us public API.
Home-page: https://github.com/nenyehub/binanceus-python
License: MIT
Keywords: Binance,trading,crypto
Author: Nenye Ndili
Author-email: nenye@ndili.net
Requires-Python: >=3.7,<4.0
Classifier: Intended Audience :: Developers
Classifier: License :: OSI Approved :: MIT License
Classifier: Natural Language :: English
Classifier: Programming Language :: Python :: 3
Classifier: Programming Language :: Python :: 3.10
Classifier: Programming Language :: Python :: 3.7
Classifier: Programming Language :: Python :: 3.8
Classifier: Programming Language :: Python :: 3.9
Requires-Dist: binance-connector (>=1.11.0,<2.0.0)
Requires-Dist: requests (>=2.27.1,<3.0.0)
Requires-Dist: websocket-client (>=1.3.1,<2.0.0)
Project-URL: Repository, https://github.com/nenyehub/binanceus-python
